dycw_template/__init__.py
dycw_template/py.typed
dycw_template-0.1.15.dist-info/WHEEL
dycw_template-0.1.15.dist-info/METADATA
dycw_template-0.1.15.dist-info/RECORD
