Metadata-Version: 2.1
Name: dycw-template
Version: 0.1.15
Summary: DYCW template package
Author: Derek Wan
Author-email: d.wan@icloud.com
Requires-Python: >=3.9,<4.0
Classifier: Programming Language :: Python :: 3
Classifier: Programming Language :: Python :: 3.10
Classifier: Programming Language :: Python :: 3.9
